Metadata-Version: 2.1
Name: crypto-stocks
Version: 0.1.5
Summary: Get current price of crypto from most popular stock exchanges
Home-page: https://github.com/mishagavura
Author-email: 1mgavura@gmail.com
License: UNKNOWN
Platform: UNKNOWN
